CONTRIBUTING.md
LICENSE
MANIFEST.in
README.md
requirements.txt
setup.py
docs/template/docker_client.md
docs/template/docker_objects/builders.md
docs/template/docker_objects/configs.md
docs/template/docker_objects/containers.md
docs/template/docker_objects/images.md
docs/template/docker_objects/networks.md
docs/template/docker_objects/nodes.md
docs/template/docker_objects/plugins.md
docs/template/docker_objects/services.md
docs/template/docker_objects/tasks.md
docs/template/docker_objects/volumes.md
docs/template/sub-commands/buildx.md
docs/template/sub-commands/compose.md
docs/template/user_guide/docker_run.md
docs/template/user_guide/exceptions.md
docs/template/user_guide/generic_resources.md
docs/template/user_guide/running_inside_a_container.md
src/pydock/__init__.py
src/pydock/client_config.py
src/pydock/command_line_entrypoint.py
src/pydock/docker_client.py
src/pydock/download_binaries.py
src/pydock/exceptions.py
src/pydock/py.typed
src/pydock/test_utils.py
src/pydock/utils.py
src/pydock.egg-info/PKG-INFO
src/pydock.egg-info/SOURCES.txt
src/pydock.egg-info/dependency_links.txt
src/pydock.egg-info/entry_points.txt
src/pydock.egg-info/requires.txt
src/pydock.egg-info/top_level.txt
src/pydock/components/__init__.py
src/pydock/components/buildx/__init__.py
src/pydock/components/buildx/cli_wrapper.py
src/pydock/components/buildx/models.py
src/pydock/components/buildx/imagetools/__init__.py
src/pydock/components/buildx/imagetools/cli_wrapper.py
src/pydock/components/buildx/imagetools/models.py
src/pydock/components/compose/__init__.py
src/pydock/components/compose/cli_wrapper.py
src/pydock/components/compose/models.py
src/pydock/components/config/__init__.py
src/pydock/components/config/cli_wrapper.py
src/pydock/components/config/models.py
src/pydock/components/container/__init__.py
src/pydock/components/container/cli_wrapper.py
src/pydock/components/container/models.py
src/pydock/components/context/__init__.py
src/pydock/components/context/cli_wrapper.py
src/pydock/components/context/models.py
src/pydock/components/image/__init__.py
src/pydock/components/image/cli_wrapper.py
src/pydock/components/image/models.py
src/pydock/components/manifest/__init__.py
