Metadata-Version: 2.1
Name: pydock
Version: 0.0.8
Summary: A decent Python wrapper for Docker CLI
Home-page: UNKNOWN
License: MIT
Project-URL: Documentation, https://duckietown.github.io/pydock/
Project-URL: Source Code, https://github.com/duckietown/pydock
Project-URL: Bug Tracker, https://github.com/duckietown/pydock/issues
Platform: UNKNOWN
Requires-Python: >=3.7, <4
License-File: LICENSE
